githubgql/__init__.py
githubgql/githubgql.py
githubgql-0.0.8.0.dist-info/LICENSE
githubgql-0.0.8.0.dist-info/METADATA
githubgql-0.0.8.0.dist-info/WHEEL
githubgql-0.0.8.0.dist-info/top_level.txt
githubgql-0.0.8.0.dist-info/RECORD
