Metadata-Version: 2.1
Name: githubgql
Version: 0.0.8.0
Summary: Python library for GraphQL API interactions on Github Actions
Home-page: https://github.com/actions-automation/githubgql
Author: Mark Bestavros
Author-email: markbest@bu.edu
License: UNKNOWN
Platform: UNKNOWN
Classifier: Programming Language :: Python :: 3
Classifier: License :: OSI Approved :: Apache Software License
Classifier: Operating System :: OS Independent
Requires-Python: >=3.6
